GateTutorial/Yosys/Gates.v
`timescale 1ns / 1ps
//////////////////////////////////////////////////////////////////////////////////
// Gates demonstration //
//////////////////////////////////////////////////////////////////////////////////

module Gates
(   input a,
    input b,
    input c,
    output out
    );
// VAR //
wire and_out;
wire or_out;
// Combinatorial //
assign and_out = a & b;
assign or_out  = a | b;
assign out = (and_out & ~c) | (or_out & c);
//
endmodule

GateTutorial/Yosys/testbench/Gates_tb.v
// Gates Test Bench
// borrowed material to understand test vector from 
// https://syssec.ethz.ch/content/dam/ethz/special-interest/infk/inst-infsec/system-security-group-dam/education/Digitaltechnik_14/14_Verilog_Testbenches.pdf
`timescale 1ns / 1ps

// Empty module cuz testbench is closed
module Gates_tb;
    // reg in
    reg a, b, c, out_t;        // gate in and target
    reg [3:0] testvector[99:0]; // test vector array
    // wire out
    wire out;
    // period = 20 * timescale = 20 * 1ns = 20ns
    localparam period = 20;

    Gates DUT(.a(a), .b(b), .c(c), .out(out));

    integer i = 0;
    initial
        begin
            $dumpfile("Gatestb.vcd");
            $dumpvars(0,Gates_tb);
            a = 0; b = 0; c = 0; out_t = 0;
            $readmemb("./testbench/TestVector.tv", testvector);
            for(i = 0; i < 8; i = i + 1)
            begin
                #period; {a, b, c, out_t} = testvector[i];
                $monitor("Test Output: %b , %b, %b, %b, %b", a, b, c, out_t, out);
            end
            #period
            $finish;
        end
endmodule

GateTutorial/Yosys/Gatestb.vcd
$date
	Sat Feb 19 15:34:44 2022
$end
$version
	Icarus Verilog
$end
$timescale
	1ps
$end
$scope module Gates_tb $end
$var wire 1 ! out $end
$var reg 1 " a $end
$var reg 1 # b $end
$var reg 1 $ c $end
$var reg 1 % out_t $end
$var integer 32 & i [31:0] $end
$scope module DUT $end
$var wire 1 " a $end
$var wire 1 ' and_out $end
$var wire 1 # b $end
$var wire 1 $ c $end
$var wire 1 ( or_out $end
$var wire 1 ! out $end
$upscope $end
$upscope $end
$enddefinitions $end
#0
$dumpvars
0(
0'
b0 &
0%
0$
0#
0"
0!
$end
#20000
b1 &
#40000
b10 &
1$
#60000
1(
b11 &
1#
0$
#80000
1!
b100 &
1$
1%
#100000
0!
b101 &
1"
0#
0$
0%
#120000
1!
b110 &
1$
1%
#140000
1!
1'
b111 &
1#
0$
#160000
b1000 &
1$
